sfo/__init__.py
sfo/utils.py
sfo-0.0.2.dist-info/METADATA
sfo-0.0.2.dist-info/WHEEL
sfo-0.0.2.dist-info/top_level.txt
sfo-0.0.2.dist-info/RECORD
