Metadata-Version: 2.1
Name: sfo
Version: 0.0.2
Summary: Sacred File Observer utilities
Home-page: https://pypi.org/project/sfo/
Author: Sumner Magruder
Author-email: sumner.magruder@zmnh.uni-hamburg.de
License: UNKNOWN
Platform: UNKNOWN
Classifier: Programming Language :: Python :: 3.5
Classifier: License :: OSI Approved :: MIT License
Classifier: Operating System :: OS Independent
